[
    {
        "first": "Redhouane",
        "last": "Abdellah",
        "marks": [1017,556,0,150,30]
    },
    {
        "first": "Hiba",
        "last": "Hamidi",
        "marks": [584,335,0,100,80]
    },
    {
        "first" :"Allae",
        "last" :"Benhassaini",
        "marks": [0,296,0,0,1]
    },
    {
        "first": "Sana",
        "last": "Berberi",
        "marks": [0,0,0,0,0]
    },
    {
        "first": "Kheira",
        "last": "Mihoub",
        "marks": [743,451,0,118,0]
    },
    {
        "first": "Ikram",
        "last": "Hamid",
        "marks": [0,0,0,0,0]
    },
    {
        "first": "Ines",
        "last": "Messadia",
        "marks": [0,100,0,0,0]
    },
    {
        "first": "Sirin",
        "last": "Soualmia",
        "marks": [0,441,0,56,0]
    },
    {
        "first": "Iyed",
        "last": "Baassou",
        "marks": [0,60,0,56,0]
    },
    {
        "first": "Mohamed Ikbal",
        "last": "Tebib",
        "marks": [0,175,0,64,150]
    },
    {
        "first": "Maria Aicha",
        "last": "Kaloune",
        "marks": [660,0,0,0,0]
    }
]
